mdurl/__init__.py
mdurl/_decode.py
mdurl/_encode.py
mdurl/_format.py
mdurl/_parse.py
mdurl/py.typed
mdurl-0.0.1.dist-info/LICENSE
mdurl-0.0.1.dist-info/WHEEL
mdurl-0.0.1.dist-info/METADATA
mdurl-0.0.1.dist-info/RECORD
